DIYables_MicroPython_Button/DIYables_MicroPython_Button.py
DIYables_MicroPython_Button/__init__.py
DIYables_MicroPython_Button-0.1.0.dist-info/LICENSE
DIYables_MicroPython_Button-0.1.0.dist-info/METADATA
DIYables_MicroPython_Button-0.1.0.dist-info/WHEEL
DIYables_MicroPython_Button-0.1.0.dist-info/top_level.txt
DIYables_MicroPython_Button-0.1.0.dist-info/RECORD
